odoo8_addon_business_product_location-8.0.1.0.0-py2.7-nspkg.pth
odoo8_addon_business_product_location-8.0.1.0.0.dist-info/DESCRIPTION.rst
odoo8_addon_business_product_location-8.0.1.0.0.dist-info/METADATA
odoo8_addon_business_product_location-8.0.1.0.0.dist-info/RECORD
odoo8_addon_business_product_location-8.0.1.0.0.dist-info/WHEEL
odoo8_addon_business_product_location-8.0.1.0.0.dist-info/metadata.json
odoo8_addon_business_product_location-8.0.1.0.0.dist-info/namespace_packages.txt
odoo8_addon_business_product_location-8.0.1.0.0.dist-info/top_level.txt
odoo_addons/business_product_location/README.rst
odoo_addons/business_product_location/__init__.py
odoo_addons/business_product_location/__openerp__.py
odoo_addons/business_product_location/i18n/am.po
odoo_addons/business_product_location/i18n/ar.po
odoo_addons/business_product_location/i18n/bg.po
odoo_addons/business_product_location/i18n/bs.po
odoo_addons/business_product_location/i18n/business_product_location.pot
odoo_addons/business_product_location/i18n/ca.po
odoo_addons/business_product_location/i18n/cs.po
odoo_addons/business_product_location/i18n/da.po
odoo_addons/business_product_location/i18n/de.po
odoo_addons/business_product_location/i18n/el_GR.po
odoo_addons/business_product_location/i18n/en_GB.po
odoo_addons/business_product_location/i18n/es.po
odoo_addons/business_product_location/i18n/es_AR.po
odoo_addons/business_product_location/i18n/es_CL.po
odoo_addons/business_product_location/i18n/es_CO.po
odoo_addons/business_product_location/i18n/es_CR.po
odoo_addons/business_product_location/i18n/es_DO.po
odoo_addons/business_product_location/i18n/es_EC.po
odoo_addons/business_product_location/i18n/es_ES.po
odoo_addons/business_product_location/i18n/es_MX.po
odoo_addons/business_product_location/i18n/es_PE.po
odoo_addons/business_product_location/i18n/es_PY.po
odoo_addons/business_product_location/i18n/es_VE.po
odoo_addons/business_product_location/i18n/et.po
odoo_addons/business_product_location/i18n/fa.po
odoo_addons/business_product_location/i18n/fi.po
odoo_addons/business_product_location/i18n/fr.po
odoo_addons/business_product_location/i18n/fr_CA.po
odoo_addons/business_product_location/i18n/fr_CH.po
odoo_addons/business_product_location/i18n/fr_FR.po
odoo_addons/business_product_location/i18n/gl.po
odoo_addons/business_product_location/i18n/gl_ES.po
odoo_addons/business_product_location/i18n/he.po
odoo_addons/business_product_location/i18n/hr.po
